[
    {
        "imdb_id": "m0451148",
        "name": "Aamir Khan"
    },
    {
        "imdb_id": "m0004487",
        "name": "Juhi Chawla"
    },
    {
        "imdb_id": "m0438474",
        "name": "Goga Kapoor"
    },
    {
        "imdb_id": "m0846681",
        "name": "Dalip Tahil"
    },
    {
        "imdb_id": "m1090174",
        "name": "Ravindra Kapoor"
    },
    {
        "imdb_id": "m0788861",
        "name": "Asha Sharma"
    },
    {
        "imdb_id": "m0622186",
        "name": "Alok Nath"
    },
    {
        "imdb_id": "m0958861",
        "name": "Raj Zutshi"
    },
    {
        "imdb_id": "m1617755",
        "name": "Shehnaz Kudia"
    },
    {
        "imdb_id": "m1401801",
        "name": "Charushila"
    },
    {
        "imdb_id": "m0066455",
        "name": "Beena Banerjee"
    },
    {
        "imdb_id": "m0481363",
        "name": "Reema Lagoo"
    },
    {
        "imdb_id": "m0856900",
        "name": "Nandita Thakur"
    },
    {
        "imdb_id": "m0451156",
        "name": "Ahmed Khan"
    },
    {
        "imdb_id": "m1019296",
        "name": "Arjun"
    },
    {
        "imdb_id": "m0882892",
        "name": "Ajit Vachani"
    },
    {
        "imdb_id": "m0664109",
        "name": "Yunus Parvez"
    },
    {
        "imdb_id": "m0451864",
        "name": "Viju Khote"
    },
    {
        "imdb_id": "m2136994",
        "name": "Babbanlal Yadav"
    },
    {
        "imdb_id": "m1217219",
        "name": "Arun Mathur"
    },
    {
        "imdb_id": "m1403762",
        "name": "Seema Vaz"
    },
    {
        "imdb_id": "m0611480",
        "name": "Mukesh"
    },
    {
        "imdb_id": "m1185344",
        "name": "Shehzad Khan"
    },
    {
        "imdb_id": "m0221218",
        "name": "Makrand Deshpande"
    },
    {
        "imdb_id": "m1244971",
        "name": "Yatin Karyekar"
    },
    {
        "imdb_id": "m1064300",
        "name": "Shiva Rindani"
    },
    {
        "imdb_id": "m0329702",
        "name": "Brij Gopal"
    },
    {
        "imdb_id": "m0882288",
        "name": "Usha"
    },
    {
        "imdb_id": "m1522170",
        "name": "Afzal"
    },
    {
        "imdb_id": "m0451207",
        "name": "Faisal Khan"
    },
    {
        "imdb_id": "m1493754",
        "name": "Noora"
    },
    {
        "imdb_id": "m0951149",
        "name": "Yusuf"
    },
    {
        "imdb_id": "m1405359",
        "name": "Imran Khan"
    },
    {
        "imdb_id": "m2776297",
        "name": "Charusheela Sabale"
    },
    {
        "imdb_id": "m1548528",
        "name": "Chhaya"
    }
]